jaguardb_socket_client/JaguarSocketClient.py
jaguardb_socket_client/LICENSE
jaguardb_socket_client/README.md
jaguardb_socket_client/__init__.py
jaguardb_socket_client/jaguarpy.so
jaguardb_socket_client/libJaguarClient.so
jaguardb_socket_client-3.5.0.1.data/data/jaguardb/JaguarSocketClient.py
jaguardb_socket_client-3.5.0.1.data/data/jaguardb/LICENSE
jaguardb_socket_client-3.5.0.1.data/data/jaguardb/README.md
jaguardb_socket_client-3.5.0.1.data/data/jaguardb/jaguarpy.so
jaguardb_socket_client-3.5.0.1.data/data/jaguardb/libJaguarClient.so
jaguardb_socket_client-3.5.0.1.dist-info/METADATA
jaguardb_socket_client-3.5.0.1.dist-info/WHEEL
jaguardb_socket_client-3.5.0.1.dist-info/top_level.txt
jaguardb_socket_client-3.5.0.1.dist-info/RECORD
