Metadata-Version: 2.1
Name: jaguardb-socket-client
Version: 3.5.0.1
Summary: Socket client for Jaguar vector database
Home-page: http://www.jaguardb.com
Author: JaguarDB
License: Apache 2.0
Platform: UNKNOWN
Requires-Python: >=3.0
